{
  "hash": "a51d71e5",
  "configHash": "153127c1",
  "lockfileHash": "19ece75b",
  "browserHash": "d09a64db",
  "optimized": {
    "framer-motion": {
      "src": "../../node_modules/framer-motion/dist/es/index.mjs",
      "file": "framer-motion.js",
      "fileHash": "7058ba36",
      "needsInterop": false
    },
    "react-dom/client": {
      "src": "../../node_modules/react-dom/client.js",
      "file": "react-dom_client.js",
      "fileHash": "c81b92f6",
      "needsInterop": true
    },
    "react-icons/fi": {
      "src": "../../node_modules/react-icons/fi/index.mjs",
      "file": "react-icons_fi.js",
      "fileHash": "7ba3fde9",
      "needsInterop": false
    },
    "react-icons/hi": {
      "src": "../../node_modules/react-icons/hi/index.mjs",
      "file": "react-icons_hi.js",
      "fileHash": "61b43581",
      "needsInterop": false
    },
    "react": {
      "src": "../../node_modules/react/index.js",
      "file": "react.js",
      "fileHash": "9c5c2382",
      "needsInterop": true
    },
    "react/jsx-dev-runtime": {
      "src": "../../node_modules/react/jsx-dev-runtime.js",
      "file": "react_jsx-dev-runtime.js",
      "fileHash": "8b49d1b6",
      "needsInterop": true
    }
  },
  "chunks": {
    "iconBase-F_bbY9sn": {
      "file": "iconBase-F_bbY9sn.js",
      "isDynamicEntry": false
    },
    "react-CZunmVaX": {
      "file": "react-CZunmVaX.js",
      "isDynamicEntry": false
    }
  }
}